color_mapper/__init__.py
color_mapper/interpolator.py
color_mapper/normalizer.py
color_mapper/utils.py
tests/__init__.py
tests/test_color_mapper.py
color_mapper-0.1.0.dist-info/LICENSE
color_mapper-0.1.0.dist-info/METADATA
color_mapper-0.1.0.dist-info/WHEEL
color_mapper-0.1.0.dist-info/top_level.txt
color_mapper-0.1.0.dist-info/RECORD
