Metadata-Version: 2.1
Name: color_mapper
Version: 0.1.0
Summary: A package for normalizing values and mapping them to a color gradient.
Home-page: https://github.com/psymoniko/color_mapper
Author: Ali Mohammadnia
Author-email: alimohammadnia127@example.com
License: MIT
Classifier: Programming Language :: Python :: 3
Classifier: License :: OSI Approved :: MIT License
Classifier: Operating System :: OS Independent
Requires-Python: >=3.6
License-File: LICENSE
Requires-Dist: matplotlib
